{"columns": ["Name", "Average Price", "Total Market", "Total Quantity", "cost", "id", "Price/Cost"], "items": [{"Name": "Thavnairian Almandine", "Average Price": 4383, "Total Market": 20963527, "Total Quantity": 4782, "cost": 20, "id": 37825, "Price/Cost": 219.15}, {"Name": "Vanadinite", "Average Price": 4685, "Total Market": 31634636, "Total Quantity": 6751, "cost": 20, "id": 37828, "Price/Cost": 234.25}, {"Name": "Palebloom Kudzu Cloth", "Average Price": 4451, "Total Market": 27920121, "Total Quantity": 6272, "cost": 20, "id": 37829, "Price/Cost": 222.55}, {"Name": "Titanoboa Skin", "Average Price": 4457, "Total Market": 26856210, "Total Quantity": 6025, "cost": 20, "id": 37827, "Price/Cost": 222.85}, {"Name": "Hannish Varnish", "Average Price": 4675, "Total Market": 17085595, "Total Quantity": 3654, "cost": 20, "id": 37826, "Price/Cost": 233.75}, {"Name": "Palaka Mistletoe", "Average Price": 2690, "Total Market": 35427340, "Total Quantity": 13166, "cost": 20, "id": 37823, "Price/Cost": 134.5}, {"Name": "Alchemical Abrasive", "Average Price": 32, "Total Market": 32614, "Total Quantity": 1005, "cost": 10, "id": 36219, "Price/Cost": 3.2}, {"Name": "Thavnairian Thread", "Average Price": 312, "Total Market": 119947, "Total Quantity": 384, "cost": 10, "id": 36221, "Price/Cost": 31.2}, {"Name": "Amynodon Hide", "Average Price": 590, "Total Market": 113892, "Total Quantity": 193, "cost": 10, "id": 36222, "Price/Cost": 59.0}, {"Name": "Thavnairian Horsetail", "Average Price": 162, "Total Market": 78582, "Total Quantity": 483, "cost": 10, "id": 36220, "Price/Cost": 16.2}, {"Name": "Alchemical Charcoal", "Average Price": 1056, "Total Market": 744603, "Total Quantity": 705, "cost": 10, "id": 36218, "Price/Cost": 105.6}]}