{"columns": ["Name", "Average Price", "Total Market", "Total Quantity", "id"], "items": [{"Name": "Carrot Pudding", "Average Price": 2604, "Total Market": 41287647, "Total Quantity": 15850, "id": 38264}, {"Name": "Garlean Pizza", "Average Price": 4089, "Total Market": 5398649, "Total Quantity": 1320, "id": 38268}, {"Name": "Gyros", "Average Price": 3157, "Total Market": 1367160, "Total Quantity": 433, "id": 38265}, {"Name": "King Urchin Loaf", "Average Price": 6086, "Total Market": 109550, "Total Quantity": 18, "id": 38270}, {"Name": "Loaghtan Rump Steak", "Average Price": 7497, "Total Market": 149940, "Total Quantity": 20, "id": 38266}, {"Name": "Melon Juice", "Average Price": 3850, "Total Market": 2460785, "Total Quantity": 639, "id": 38262}, {"Name": "Melon Pie", "Average Price": 6882, "Total Market": 4397770, "Total Quantity": 639, "id": 38261}, {"Name": "Piennolo Tomato Salad", "Average Price": 4961, "Total Market": 3324246, "Total Quantity": 670, "id": 38267}, {"Name": "Sunset Carrot Nibbles", "Average Price": 3075, "Total Market": 12891892, "Total Quantity": 4192, "id": 38263}, {"Name": "Urchin Pasta", "Average Price": 0, "Total Market": 0, "Total Quantity": 0, "id": 38269}, {"Name": "Calamari Ripieni", "Average Price": 3787, "Total Market": 4416184, "Total Quantity": 1166, "id": 37282}, {"Name": "Kalamarakia Tiganita", "Average Price": 6126, "Total Market": 1084391, "Total Quantity": 177, "id": 37283}, {"Name": "Tsai tou Vounou", "Average Price": 1578, "Total Market": 15032548, "Total Quantity": 9524, "id": 36060}]}