{"columns": ["Name", "Average Price", "Total Market", "Total Quantity", "id"], "items": [{"Name": "Timeworn Leather Map", "Average Price": 35523, "Total Market": 923599, "Total Quantity": 26, "id": 6688}, {"Name": "Timeworn Goatskin Map", "Average Price": 4838, "Total Market": 101615, "Total Quantity": 21, "id": 6689}, {"Name": "Timeworn Toadskin Map", "Average Price": 9697, "Total Market": 271533, "Total Quantity": 28, "id": 6690}, {"Name": "Timeworn Boarskin Map", "Average Price": 27152, "Total Market": 434444, "Total Quantity": 16, "id": 6691}, {"Name": "Timeworn Peisteskin Map", "Average Price": 29677, "Total Market": 1157430, "Total Quantity": 39, "id": 6692}, {"Name": "Timeworn Archaeoskin Map", "Average Price": 12070, "Total Market": 350047, "Total Quantity": 29, "id": 12241}, {"Name": "Timeworn Wyvernskin Map", "Average Price": 28658, "Total Market": 1232304, "Total Quantity": 43, "id": 12242}, {"Name": "Timeworn Dragonskin Map", "Average Price": 33801, "Total Market": 3008331, "Total Quantity": 89, "id": 12243}, {"Name": "Timeworn Gaganaskin Map", "Average Price": 15249, "Total Market": 335479, "Total Quantity": 22, "id": 17835}, {"Name": "Timeworn Gazelleskin Map", "Average Price": 35488, "Total Market": 4968377, "Total Quantity": 140, "id": 17836}, {"Name": "Timeworn Gliderskin Map", "Average Price": 36566, "Total Market": 3108141, "Total Quantity": 85, "id": 26744}, {"Name": "Timeworn Zonureskin Map", "Average Price": 27475, "Total Market": 4588335, "Total Quantity": 167, "id": 26745}, {"Name": "Timeworn Saigaskin Map", "Average Price": 8006, "Total Market": 184142, "Total Quantity": 23, "id": 36611}, {"Name": "Timeworn Kumbhiraskin Map", "Average Price": 31204, "Total Market": 20220750, "Total Quantity": 648, "id": 36612}]}