{"columns": ["Item Name", "Average Price", "Total Market", "Total Sold", "duration", "id", "level", "quantity", "Gil/Duration*Quantity"], "items": [{"Item Name": "Double-edged Herb", "Average Price": 56, "Total Market": 27473, "Total Sold": 488, "id": 36217, "duration": 60, "level": 90, "quantity": 5, "Gil/Duration*Quantity": 4.666666666666667}, {"Item Name": "Golden Cocoon", "Average Price": 588, "Total Market": 304073, "Total Sold": 517, "id": 36207, "duration": 60, "level": 90, "quantity": 5, "Gil/Duration*Quantity": 49.0}, {"Item Name": "Mempisang Log", "Average Price": 55, "Total Market": 7872, "Total Sold": 143, "id": 36195, "duration": 60, "level": 90, "quantity": 5, "Gil/Duration*Quantity": 4.583333333333333}, {"Item Name": "Potent Spice", "Average Price": 83, "Total Market": 17270, "Total Sold": 206, "id": 36214, "duration": 60, "level": 90, "quantity": 5, "Gil/Duration*Quantity": 6.916666666666666}, {"Item Name": "Alien Onion", "Average Price": 37, "Total Market": 64411, "Total Sold": 1725, "id": 36097, "duration": 60, "level": 90, "quantity": 20, "Gil/Duration*Quantity": 12.333333333333334}, {"Item Name": "AR-Caean Cotton Boll", "Average Price": 231, "Total Market": 1375796, "Total Sold": 5942, "id": 36206, "duration": 60, "level": 89, "quantity": 20, "Gil/Duration*Quantity": 77.0}, {"Item Name": "Integral Log", "Average Price": 270, "Total Market": 1256903, "Total Sold": 4648, "id": 36194, "duration": 60, "level": 89, "quantity": 20, "Gil/Duration*Quantity": 90.0}, {"Item Name": "Elder Nutmeg Seeds", "Average Price": 134, "Total Market": 181812, "Total Sold": 1354, "id": 36095, "duration": 60, "level": 88, "quantity": 20, "Gil/Duration*Quantity": 44.66666666666667}, {"Item Name": "Sideritis Leaves", "Average Price": 248, "Total Market": 767916, "Total Sold": 3086, "id": 36094, "duration": 60, "level": 88, "quantity": 20, "Gil/Duration*Quantity": 82.66666666666667}, {"Item Name": "Giant Popoto", "Average Price": 303, "Total Market": 124515, "Total Sold": 410, "id": 36089, "duration": 60, "level": 87, "quantity": 20, "Gil/Duration*Quantity": 101.0}, {"Item Name": "Sykon", "Average Price": 368, "Total Market": 799049, "Total Sold": 2170, "id": 36096, "duration": 60, "level": 87, "quantity": 20, "Gil/Duration*Quantity": 122.66666666666667}, {"Item Name": "Ironwood Log", "Average Price": 153, "Total Market": 402147, "Total Sold": 2627, "id": 36193, "duration": 60, "level": 86, "quantity": 20, "Gil/Duration*Quantity": 51.0}, {"Item Name": "Scarlet Moko Grass", "Average Price": 281, "Total Market": 142886, "Total Sold": 508, "id": 36205, "duration": 60, "level": 86, "quantity": 20, "Gil/Duration*Quantity": 93.66666666666667}, {"Item Name": "Carrot of Happiness", "Average Price": 256, "Total Market": 327078, "Total Sold": 1274, "id": 36090, "duration": 60, "level": 85, "quantity": 30, "Gil/Duration*Quantity": 128.0}, {"Item Name": "Beet", "Average Price": 271, "Total Market": 60361, "Total Sold": 222, "id": 36093, "duration": 60, "level": 84, "quantity": 30, "Gil/Duration*Quantity": 135.5}, {"Item Name": "Red Pine Log", "Average Price": 418, "Total Market": 471615, "Total Sold": 1127, "id": 36192, "duration": 60, "level": 84, "quantity": 30, "Gil/Duration*Quantity": 209.0}, {"Item Name": "Snow Flax", "Average Price": 266, "Total Market": 490336, "Total Sold": 1843, "id": 36204, "duration": 60, "level": 84, "quantity": 30, "Gil/Duration*Quantity": 133.0}, {"Item Name": "Cucumber", "Average Price": 285, "Total Market": 91810, "Total Sold": 322, "id": 36091, "duration": 60, "level": 83, "quantity": 30, "Gil/Duration*Quantity": 142.5}, {"Item Name": "Eblan Lentils", "Average Price": 277, "Total Market": 53225, "Total Sold": 192, "id": 36092, "duration": 60, "level": 83, "quantity": 30, "Gil/Duration*Quantity": 138.5}, {"Item Name": "Coconut", "Average Price": 255, "Total Market": 37535, "Total Sold": 147, "id": 36087, "duration": 60, "level": 82, "quantity": 40, "Gil/Duration*Quantity": 170.0}, {"Item Name": "Palm Log", "Average Price": 174, "Total Market": 121912, "Total Sold": 700, "id": 36191, "duration": 60, "level": 82, "quantity": 40, "Gil/Duration*Quantity": 116.0}, {"Item Name": "Palm Syrup", "Average Price": 290, "Total Market": 1603957, "Total Sold": 5521, "id": 36086, "duration": 60, "level": 82, "quantity": 40, "Gil/Duration*Quantity": 193.33333333333331}, {"Item Name": "Thavnairian Paprika", "Average Price": 326, "Total Market": 115719, "Total Sold": 354, "id": 36098, "duration": 60, "level": 82, "quantity": 40, "Gil/Duration*Quantity": 217.33333333333334}, {"Item Name": "Thavnairian Perilla Leaf", "Average Price": 386, "Total Market": 1330064, "Total Sold": 3442, "id": 36085, "duration": 60, "level": 82, "quantity": 40, "Gil/Duration*Quantity": 257.33333333333337}, {"Item Name": "Dark Hemp", "Average Price": 436, "Total Market": 231373, "Total Sold": 530, "id": 36202, "duration": 60, "level": 81, "quantity": 40, "Gil/Duration*Quantity": 290.6666666666667}, {"Item Name": "Dark Rye", "Average Price": 348, "Total Market": 10440, "Total Sold": 30, "id": 36083, "duration": 60, "level": 81, "quantity": 40, "Gil/Duration*Quantity": 232.0}, {"Item Name": "Horse Chestnut Log", "Average Price": 442, "Total Market": 501315, "Total Sold": 1134, "id": 36190, "duration": 60, "level": 81, "quantity": 40, "Gil/Duration*Quantity": 294.66666666666663}, {"Item Name": "Iceberg Lettuce", "Average Price": 448, "Total Market": 55119, "Total Sold": 123, "id": 36088, "duration": 60, "level": 81, "quantity": 40, "Gil/Duration*Quantity": 298.6666666666667}, {"Item Name": "Lemonette", "Average Price": 657, "Total Market": 1941915, "Total Sold": 2954, "id": 27835, "duration": 60, "level": 80, "quantity": 9, "Gil/Duration*Quantity": 98.55}, {"Item Name": "Lignum Vitae Log", "Average Price": 390, "Total Market": 735310, "Total Sold": 1882, "id": 27687, "duration": 60, "level": 80, "quantity": 50, "Gil/Duration*Quantity": 325.0}, {"Item Name": "Ethereal Cocoon", "Average Price": 855, "Total Market": 303754, "Total Sold": 355, "id": 27761, "duration": 60, "level": 80, "quantity": 9, "Gil/Duration*Quantity": 128.25}, {"Item Name": "Sandalwood Log", "Average Price": 396, "Total Market": 98232, "Total Sold": 248, "id": 27688, "duration": 60, "level": 80, "quantity": 9, "Gil/Duration*Quantity": 59.4}, {"Item Name": "Sandalwood Sap", "Average Price": 0, "Total Market": 0, "Total Sold": 0, "id": 28716, "duration": 60, "level": 80, "quantity": 9, "Gil/Duration*Quantity": 0.0}, {"Item Name": "Duskblooms", "Average Price": 1648, "Total Market": 700759, "Total Sold": 425, "id": 29974, "duration": 60, "level": 80, "quantity": 9, "Gil/Duration*Quantity": 247.2}, {"Item Name": "Imperial Fern", "Average Price": 288, "Total Market": 10389, "Total Sold": 36, "id": 29978, "duration": 60, "level": 80, "quantity": 9, "Gil/Duration*Quantity": 43.199999999999996}, {"Item Name": "Merbau Log", "Average Price": 696, "Total Market": 153271, "Total Sold": 220, "id": 29972, "duration": 60, "level": 80, "quantity": 9, "Gil/Duration*Quantity": 104.39999999999999}, {"Item Name": "Tender Dill", "Average Price": 791, "Total Market": 182149, "Total Sold": 230, "id": 30485, "duration": 60, "level": 80, "quantity": 9, "Gil/Duration*Quantity": 118.65}, {"Item Name": "Raindrop Cotton Boll", "Average Price": 618, "Total Market": 82940, "Total Sold": 134, "id": 32953, "duration": 60, "level": 80, "quantity": 8, "Gil/Duration*Quantity": 82.4}, {"Item Name": "Silver Beech Log", "Average Price": 443, "Total Market": 8860, "Total Sold": 20, "id": 32950, "duration": 60, "level": 80, "quantity": 8, "Gil/Duration*Quantity": 59.06666666666667}, {"Item Name": "Wattle Petribark", "Average Price": 136, "Total Market": 21043, "Total Sold": 154, "id": 32954, "duration": 60, "level": 80, "quantity": 8, "Gil/Duration*Quantity": 18.133333333333333}, {"Item Name": "Dwarven Cotton Boll", "Average Price": 199, "Total Market": 304770, "Total Sold": 1527, "id": 27759, "duration": 50, "level": 79, "quantity": 50, "Gil/Duration*Quantity": 199.0}, {"Item Name": "Light Gerbera", "Average Price": 411, "Total Market": 1630566, "Total Sold": 3967, "id": 27785, "duration": 50, "level": 79, "quantity": 50, "Gil/Duration*Quantity": 411.00000000000006}, {"Item Name": "Tiger Lily", "Average Price": 112, "Total Market": 154897, "Total Sold": 1377, "id": 27784, "duration": 50, "level": 79, "quantity": 50, "Gil/Duration*Quantity": 112.00000000000001}, {"Item Name": "Bomba Rice", "Average Price": 86, "Total Market": 947, "Total Sold": 11, "id": 27830, "duration": 50, "level": 78, "quantity": 50, "Gil/Duration*Quantity": 86.0}, {"Item Name": "Coffee Beans", "Average Price": 134, "Total Market": 59968, "Total Sold": 447, "id": 27837, "duration": 50, "level": 78, "quantity": 50, "Gil/Duration*Quantity": 134.0}, {"Item Name": "Harcot", "Average Price": 102, "Total Market": 6735, "Total Sold": 66, "id": 27819, "duration": 50, "level": 78, "quantity": 50, "Gil/Duration*Quantity": 102.0}, {"Item Name": "Lime Basil", "Average Price": 313, "Total Market": 576359, "Total Sold": 1836, "id": 27783, "duration": 50, "level": 78, "quantity": 50, "Gil/Duration*Quantity": 313.0}, {"Item Name": "Mist Spinach", "Average Price": 4, "Total Market": 403, "Total Sold": 84, "id": 27828, "duration": 50, "level": 78, "quantity": 9, "Gil/Duration*Quantity": 0.72}, {"Item Name": "Fernleaf Lavender", "Average Price": 286, "Total Market": 221089, "Total Sold": 772, "id": 27780, "duration": 50, "level": 77, "quantity": 50, "Gil/Duration*Quantity": 286.0}, {"Item Name": "Amber Cloves", "Average Price": 183, "Total Market": 26231, "Total Sold": 143, "id": 27821, "duration": 50, "level": 76, "quantity": 50, "Gil/Duration*Quantity": 183.0}, {"Item Name": "Russet Popoto", "Average Price": 6, "Total Market": 310, "Total Sold": 46, "id": 27822, "duration": 50, "level": 76, "quantity": 9, "Gil/Duration*Quantity": 1.08}, {"Item Name": "Sandteak Log", "Average Price": 367, "Total Market": 314166, "Total Sold": 855, "id": 27686, "duration": 50, "level": 76, "quantity": 50, "Gil/Duration*Quantity": 367.0}, {"Item Name": "Sweet Alyssum", "Average Price": 282, "Total Market": 510620, "Total Sold": 1807, "id": 27779, "duration": 50, "level": 76, "quantity": 50, "Gil/Duration*Quantity": 282.0}, {"Item Name": "Creamtop Mushroom", "Average Price": 209, "Total Market": 119486, "Total Sold": 571, "id": 27829, "duration": 50, "level": 75, "quantity": 50, "Gil/Duration*Quantity": 209.0}, {"Item Name": "Gianthive Chip", "Average Price": 316, "Total Market": 551073, "Total Sold": 1740, "id": 27834, "duration": 50, "level": 75, "quantity": 50, "Gil/Duration*Quantity": 316.0}, {"Item Name": "Royal Grapes", "Average Price": 420, "Total Market": 21000, "Total Sold": 50, "id": 27826, "duration": 50, "level": 75, "quantity": 50, "Gil/Duration*Quantity": 420.0}, {"Item Name": "Peppermint", "Average Price": 74, "Total Market": 24089, "Total Sold": 324, "id": 27836, "duration": 50, "level": 74, "quantity": 9, "Gil/Duration*Quantity": 13.32}, {"Item Name": "Pixie Floss Boll", "Average Price": 116, "Total Market": 90463, "Total Sold": 775, "id": 27753, "duration": 50, "level": 74, "quantity": 50, "Gil/Duration*Quantity": 115.99999999999999}, {"Item Name": "White Ash Log", "Average Price": 408, "Total Market": 321346, "Total Sold": 786, "id": 27685, "duration": 50, "level": 74, "quantity": 50, "Gil/Duration*Quantity": 408.0}, {"Item Name": "Upland Wheat", "Average Price": 315, "Total Market": 306271, "Total Sold": 971, "id": 27832, "duration": 50, "level": 73, "quantity": 50, "Gil/Duration*Quantity": 315.0}, {"Item Name": "Broad Beans", "Average Price": 25, "Total Market": 2127, "Total Sold": 84, "id": 27833, "duration": 50, "level": 72, "quantity": 9, "Gil/Duration*Quantity": 4.5}, {"Item Name": "Garden Beet", "Average Price": 299, "Total Market": 628590, "Total Sold": 2098, "id": 27824, "duration": 50, "level": 72, "quantity": 50, "Gil/Duration*Quantity": 299.0}, {"Item Name": "Iridescent Cocoon", "Average Price": 220, "Total Market": 13653, "Total Sold": 62, "id": 27750, "duration": 50, "level": 72, "quantity": 50, "Gil/Duration*Quantity": 220.00000000000003}, {"Item Name": "Miracle Apple Log", "Average Price": 60, "Total Market": 35395, "Total Sold": 583, "id": 27684, "duration": 50, "level": 72, "quantity": 50, "Gil/Duration*Quantity": 60.0}, {"Item Name": "Blood Tomato", "Average Price": 215, "Total Market": 116599, "Total Sold": 542, "id": 27825, "duration": 50, "level": 71, "quantity": 50, "Gil/Duration*Quantity": 215.0}, {"Item Name": "Bright Flax", "Average Price": 332, "Total Market": 715689, "Total Sold": 2152, "id": 27747, "duration": 50, "level": 71, "quantity": 50, "Gil/Duration*Quantity": 332.0}, {"Item Name": "Curly Parsley", "Average Price": 321, "Total Market": 60368, "Total Sold": 188, "id": 27823, "duration": 50, "level": 71, "quantity": 50, "Gil/Duration*Quantity": 321.0}, {"Item Name": "Frantoio", "Average Price": 252, "Total Market": 123913, "Total Sold": 491, "id": 27820, "duration": 50, "level": 71, "quantity": 50, "Gil/Duration*Quantity": 252.0}, {"Item Name": "Pixie Apple", "Average Price": 300, "Total Market": 5400, "Total Sold": 18, "id": 27831, "duration": 50, "level": 71, "quantity": 50, "Gil/Duration*Quantity": 300.0}, {"Item Name": "Purple Carrot", "Average Price": 222, "Total Market": 65465, "Total Sold": 294, "id": 27818, "duration": 50, "level": 71, "quantity": 50, "Gil/Duration*Quantity": 222.00000000000003}, {"Item Name": "White Oak Branch", "Average Price": 596, "Total Market": 29800, "Total Sold": 50, "id": 27816, "duration": 50, "level": 71, "quantity": 50, "Gil/Duration*Quantity": 596.0}, {"Item Name": "White Oak Log", "Average Price": 23, "Total Market": 22198, "Total Sold": 934, "id": 27683, "duration": 50, "level": 71, "quantity": 50, "Gil/Duration*Quantity": 23.0}, {"Item Name": "Othardian Plum", "Average Price": 70, "Total Market": 3512, "Total Sold": 50, "id": 19852, "duration": 50, "level": 70, "quantity": 50, "Gil/Duration*Quantity": 70.0}, {"Item Name": "Zelkova Log", "Average Price": 181, "Total Market": 312338, "Total Sold": 1717, "id": 19933, "duration": 50, "level": 70, "quantity": 50, "Gil/Duration*Quantity": 181.0}, {"Item Name": "Azim Cotton Boll", "Average Price": 0, "Total Market": 0, "Total Sold": 0, "id": 21086, "duration": 50, "level": 70, "quantity": 50, "Gil/Duration*Quantity": 0.0}, {"Item Name": "Hallowed Basil", "Average Price": 1, "Total Market": 44, "Total Sold": 34, "id": 19918, "duration": 50, "level": 70, "quantity": 50, "Gil/Duration*Quantity": 1.0}, {"Item Name": "Rhea", "Average Price": 0, "Total Market": 0, "Total Sold": 0, "id": 19991, "duration": 50, "level": 70, "quantity": 50, "Gil/Duration*Quantity": 0.0}, {"Item Name": "Torreya Log", "Average Price": 570, "Total Market": 338018, "Total Sold": 593, "id": 19934, "duration": 50, "level": 70, "quantity": 50, "Gil/Duration*Quantity": 570.0}, {"Item Name": "Black Willow Log", "Average Price": 672, "Total Market": 55176, "Total Sold": 82, "id": 22419, "duration": 50, "level": 70, "quantity": 50, "Gil/Duration*Quantity": 672.0}, {"Item Name": "Hardened Veteran Tree Sap", "Average Price": 0, "Total Market": 0, "Total Sold": 0, "id": 23180, "duration": 50, "level": 70, "quantity": 50, "Gil/Duration*Quantity": 0.0}, {"Item Name": "Hingan Flax", "Average Price": 603, "Total Market": 51931, "Total Sold": 86, "id": 22420, "duration": 50, "level": 70, "quantity": 50, "Gil/Duration*Quantity": 603.0}, {"Item Name": "Night Pepper", "Average Price": 222, "Total Market": 56157, "Total Sold": 252, "id": 27827, "duration": 50, "level": 70, "quantity": 50, "Gil/Duration*Quantity": 222.00000000000003}, {"Item Name": "Urunday Log", "Average Price": 0, "Total Market": 0, "Total Sold": 0, "id": 24242, "duration": 50, "level": 70, "quantity": 50, "Gil/Duration*Quantity": 0.0}, {"Item Name": "Yanxian Cotton Boll", "Average Price": 86, "Total Market": 4829, "Total Sold": 56, "id": 24243, "duration": 50, "level": 70, "quantity": 50, "Gil/Duration*Quantity": 86.0}]}